rlpcap/__init__.py
rlpcap/sniffer.py
rlpcap/utils.py
rlpcap-1.2.0.dist-info/METADATA
rlpcap-1.2.0.dist-info/WHEEL
rlpcap-1.2.0.dist-info/entry_points.txt
rlpcap-1.2.0.dist-info/top_level.txt
rlpcap-1.2.0.dist-info/RECORD
