Metadata-Version: 2.4
Name: rlpcap
Version: 1.2.0
Summary: Simple Rocket League UDP sniffer utilities
Home-page: https://github.com/imattas/rlpcap
Author: Ian Matas
Author-email: ian@mattas.net
License: MIT
Classifier: Programming Language :: Python :: 3
Classifier: License :: OSI Approved :: MIT License
Classifier: Operating System :: OS Independent
Requires-Python: >=3.8
Requires-Dist: scapy
Requires-Dist: psutil
Requires-Dist: pyperclip
Requires-Dist: colorama
